{
  
   "services" : [
      {
        "name" : "fao-areas",
        "uri" : "http://www.fao.org/figis/geoserver/fifao/ows",
        "excludeGeom" : true,
        "compress" : true
      },
      {
        "name" : "vliz",
        "uri" : "http://geo.vliz.be/geoserver/MarineRegions/ows",
        "excludeGeom" : true
      } , 
      
      {
        "name" : "intersections",
        "uri" : "http://www.fao.org/figis/geoserver/GeoRelationship/ows",
        "excludeGeom" : true
      }  
         
   ]
   
}